jmidi/__init__.py
jmidi/jmidi.py
jmidi-1.0.dist-info/LICENSE
jmidi-1.0.dist-info/METADATA
jmidi-1.0.dist-info/WHEEL
jmidi-1.0.dist-info/top_level.txt
jmidi-1.0.dist-info/RECORD
