Metadata-Version: 2.1
Name: jmidi
Version: 1.0
Summary: Julian's MIDI Manager class
Home-page: https://github.com/julianfl0w/jmidi
Author: Julian Loiacono
Author-email: jcloiacon@gmail.com
License: UNKNOWN
Platform: UNKNOWN
